sigstore_a2a/__init__.py
sigstore_a2a/provenance.py
sigstore_a2a/signer.py
sigstore_a2a/verifier.py
sigstore_a2a/cli/__init__.py
sigstore_a2a/cli/main.py
sigstore_a2a/cli/serve.py
sigstore_a2a/cli/sign.py
sigstore_a2a/cli/verify.py
sigstore_a2a/models/__init__.py
sigstore_a2a/models/agent_card.py
sigstore_a2a/models/provenance.py
sigstore_a2a/models/signature.py
sigstore_a2a/utils/__init__.py
sigstore_a2a/utils/ci.py
sigstore_a2a/utils/crypto.py
sigstore_a2a-0.1.0.dist-info/METADATA
sigstore_a2a-0.1.0.dist-info/WHEEL
sigstore_a2a-0.1.0.dist-info/entry_points.txt
sigstore_a2a-0.1.0.dist-info/RECORD
